unsplash_dl/__main__.py
unsplash_dl/download_command.py
unsplash_dl/download_command_config.py
unsplash_dl/logger.py
unsplash_dl/unsplash_service.py
unsplash_dl-0.1.1.dist-info/METADATA
unsplash_dl-0.1.1.dist-info/WHEEL
unsplash_dl-0.1.1.dist-info/entry_points.txt
unsplash_dl-0.1.1.dist-info/RECORD
