Metadata-Version: 2.1
Name: unsplash_dl
Version: 0.1.1
Summary: 
Author: Anton
Author-email: anton@shuvalov.info
Requires-Python: >=3.11,<4.0
Classifier: Programming Language :: Python :: 3
Classifier: Programming Language :: Python :: 3.11
Requires-Dist: docopt (>=0.6.2,<0.7.0)
Requires-Dist: requests (>=2.31.0,<3.0.0)
Requires-Dist: tqdm (>=4.66.1,<5.0.0)
